hind/__init__.py
hind/__main__.py
hind/client.py
hind/configuration.py
hind-0.1.2.data/scripts/hind
hind-0.1.2.dist-info/METADATA
hind-0.1.2.dist-info/WHEEL
hind-0.1.2.dist-info/top_level.txt
hind-0.1.2.dist-info/RECORD
